tvb_kernels-0.5.dist-info/RECORD
tvb_kernels-0.5.dist-info/WHEEL
tvb_kernels-0.5.dist-info/METADATA
tvb_kernels/__init__.py
tvb_kernels/_nanobound.cpython-310-darwin.so
