Metadata-Version: 2.1
Name: tvb-kernels
Version: 0.5
Summary: TVB computational kernels
Author-Email: Marmaduke Woodman <marmaduke.woodman@univ-amu.fr>
Project-URL: Homepage, https://github.com/the-virtual-brain/tvb-root
Requires-Python: >=3.8
Requires-Dist: numpy==1.24
Requires-Dist: scipy
